setup.cfg
setup.py
elasticstats/__init__.py
elasticstats/elasticstats.py
elasticstats_scrapy.egg-info/PKG-INFO
elasticstats_scrapy.egg-info/SOURCES.txt
elasticstats_scrapy.egg-info/dependency_links.txt
elasticstats_scrapy.egg-info/requires.txt
elasticstats_scrapy.egg-info/top_level.txt