Metadata-Version: 1.0
Name: elasticstats-scrapy
Version: 0.1.5
Summary: A scrapy extension to send crawl stats to elasticsearch index.
Home-page: https://github.com/suraj-arya/elasticstats-scrapy
Author: Suraj Arya
Author-email: suraj@loanzen.in
License: MIT license
Keywords: elasticstats
Platform: UNKNOWN
